coinpay/__init__.py
coinpay/api.py
coinpay/enums.py
coinpay/processing/__init__.py
coinpay/processing/currency.py
coinpay/processing/deposit.py
coinpay/processing/exchange.py
coinpay/processing/exchange_rate.py
coinpay/processing/internal_movement.py
coinpay/processing/invoice.py
coinpay/processing/orders.py
coinpay/processing/pair.py
coinpay/processing/user.py
coinpay/processing/withdrawal.py
coinpay_sdk-0.0.3.dist-info/METADATA
coinpay_sdk-0.0.3.dist-info/WHEEL
coinpay_sdk-0.0.3.dist-info/top_level.txt
coinpay_sdk-0.0.3.dist-info/RECORD
