Metadata-Version: 2.1
Name: coinpay-sdk
Version: 0.0.3
Summary: COINPAY Software Development Kit
Home-page: https://github.com/coinpay-com-ua/python-sdk/
Author: COINPAY
Author-email: info@coinpay.ua
License: MIT License
Keywords: SDK
Platform: UNKNOWN
Classifier: Programming Language :: Python :: 3
Classifier: License :: OSI Approved :: MIT License
Classifier: Operating System :: OS Independent
Requires-Python: >=3.5
Requires-Dist: certifi
Requires-Dist: requests
